{
  "name": "Backlot - Network Diagnostics",
  "integrationType": "custom-rest-actions",
  "actionType": "custom",
  "secure": false,
  "config": {
    "request": {
      "requestUrlTemplate": "https://backlot-api.krishharness.com/gx/net-diagnostics?identifier=${esc.url(input.identifier)}",
      "requestType": "GET",
      "headers": {
        "X-API-Key": "${credentials.apiKey}"
      },
      "requestTemplate": "${input.rawRequest}"
    },
    "response": {
      "translationMap": {},
      "translationMapDefaults": {},
      "successTemplate": "${rawResult}"
    }
  },
  "contract": {
    "input": {
      "inputSchema": {
        "$schema": "http://json-schema.org/draft-04/schema#",
        "title": "Backlot - Network Diagnostics input",
        "type": "object",
        "properties": {
          "identifier": {
            "type": "string",
            "description": "Raw identifier: ANI/phone (E.164 or national), email, or account number. Normalized server-side, so an unencoded '+' is tolerated."
          }
        },
        "required": [
          "identifier"
        ],
        "additionalProperties": false
      }
    },
    "output": {
      "successSchema": {
        "$schema": "http://json-schema.org/draft-04/schema#",
        "title": "NetDiagnosticsOut output",
        "type": "object",
        "properties": {
          "found": {
            "type": "boolean",
            "description": "False when the identifier resolves to no subscriber."
          },
          "party_id": {
            "type": "string",
            "description": "Internal subscriber id. Never read it aloud."
          },
          "fault_type": {
            "type": "string",
            "description": "The single fault to act on: device_band_stuck (a device is on the slow band with a weak signal), extender_flapping (a booster keeps dropping), wan_degraded (the line into the home is down \u2014 cannot be self-healed), or none when the network is healthy."
          },
          "primary_target": {
            "type": "string",
            "description": "Opaque id of the thing to fix. Pass it straight to device-action as 'target'. Never read it aloud."
          },
          "primary_target_kind": {
            "type": "string",
            "description": "What the target is: device, ap, or gateway."
          },
          "primary_target_label": {
            "type": "string",
            "description": "Human name of the faulty thing, e.g. \"Ella's iPad\". Use this when telling the customer what you found."
          },
          "recommended_action": {
            "type": "string",
            "description": "The device-action verb to call next: band-steer, reboot-extender, escalate (a human must handle it), or none."
          },
          "wan_ok": {
            "type": "boolean",
            "description": "True when the broadband line into the home is healthy."
          },
          "worst_device_band": {
            "type": "string",
            "description": "Wi-Fi band of the weakest device: 2.4 (slower, longer range) or 5 (faster)."
          },
          "worst_device_rssi": {
            "type": "integer",
            "description": "Signal strength of the weakest device in dBm. Nearer 0 is better; below -70 is poor."
          },
          "extender_status": {
            "type": "string",
            "description": "Health of the Wi-Fi booster: online, flapping, offline, or none if there isn't one."
          }
        },
        "required": [
          "extender_status",
          "fault_type",
          "found",
          "party_id",
          "primary_target",
          "primary_target_kind",
          "primary_target_label",
          "recommended_action",
          "wan_ok",
          "worst_device_band",
          "worst_device_rssi"
        ],
        "additionalProperties": true
      }
    }
  }
}
